oximachine_featurizer/__init__.py
oximachine_featurizer/exclude.py
oximachine_featurizer/featurize.py
oximachine_featurizer/featurizer_local_property.py
oximachine_featurizer/parse.py
oximachine_featurizer/utils.py
oximachine_featurizer/data/periodic_table.json
oximachine_featurizer-0.4.0.dist-info/entry_points.txt
oximachine_featurizer-0.4.0.dist-info/LICENSE
oximachine_featurizer-0.4.0.dist-info/WHEEL
oximachine_featurizer-0.4.0.dist-info/METADATA
oximachine_featurizer-0.4.0.dist-info/RECORD
