Metadata-Version: 2.1
Name: oximachine-featurizer
Version: 0.4.0
Summary: Mine MOF oxidation states and featurize metal sites.
Author: Kevin M. Jablonka
Requires-Python: >=3.8
Classifier: Development Status :: 4 - Beta
Classifier: Intended Audience :: Science/Research
Classifier: Topic :: Scientific/Engineering :: Chemistry
Classifier: License :: OSI Approved :: MIT License
Classifier: Programming Language :: Python
Classifier: Programming Language :: Python :: 3
Classifier: Programming Language :: Python :: 3 :: Only
Classifier: Programming Language :: Python :: 3.8
Classifier: Programming Language :: Python :: 3.9
Classifier: Programming Language :: Python :: 3.10
Classifier: Programming Language :: Python :: 3.11
Requires-Dist: ase~=3.0
Requires-Dist: tqdm~=4.0
Requires-Dist: click~=8.1
Requires-Dist: matminer~=0.6
Requires-Dist: numba~=0.57
Requires-Dist: ruff ; extra == "dev"
Requires-Dist: pytest ; extra == "dev"
Requires-Dist: isort ; extra == "dev"
Requires-Dist: black ; extra == "dev"
Requires-Dist: sphinx~=3.3.1 ; extra == "docs"
Requires-Dist: sphinx-book-theme~=0.0.39 ; extra == "docs"
Requires-Dist: sphinx-autodoc-typehints~=1.11.1 ; extra == "docs"
Requires-Dist: sphinx-copybutton~=0.3.1 ; extra == "docs"
Requires-Dist: numeral~=0.1 ; extra == "full"
Requires-Dist: apricot-select~=0.6 ; extra == "full"
Requires-Dist: scikit-multilearn~=0.2 ; extra == "full"
Project-URL: Homepage, https://github.com/kjappelbaum/oximachine_featurizer
Provides-Extra: dev
Provides-Extra: docs
Provides-Extra: full
